whispercpp_kit/__init__.py
whispercpp_kit/core.py
whispercpp_kit-0.1.7.dist-info/licenses/LICENSE
whispercpp_kit-0.1.7.dist-info/METADATA
whispercpp_kit-0.1.7.dist-info/WHEEL
whispercpp_kit-0.1.7.dist-info/top_level.txt
whispercpp_kit-0.1.7.dist-info/RECORD
