Metadata-Version: 2.4
Name: whispercpp_kit
Version: 0.1.7
Summary: A toolkit for whisper.cpp with audio processing and model management
Author-email: Simeon Emanuilov <simeon.emanuilov@gmail.com>
License: MIT License
Project-URL: Homepage, https://github.com/s-emanuilov/whispercpp_kit
Keywords: whisper,speech-to-text,audio,transcription
Classifier: License :: OSI Approved :: MIT License
Classifier: Programming Language :: Python :: 3
Classifier: Programming Language :: Python :: 3.8
Classifier: Programming Language :: Python :: 3.9
Classifier: Programming Language :: Python :: 3.10
Classifier: Programming Language :: Python :: 3.11
Classifier: Programming Language :: Python :: 3.12
Requires-Python: >=3.8
License-File: LICENSE
Requires-Dist: ffmpeg-python
Provides-Extra: dev
Requires-Dist: pytest; extra == "dev"
Dynamic: license-file
